src/information_bottleneck/__init__.py
src/information_bottleneck/core.py
src/information_bottleneck/core_original_1472_lines.py
src/information_bottleneck/deep_ib.py
src/information_bottleneck/evaluation_metrics.py
src/information_bottleneck/ib_algorithms.py
src/information_bottleneck/ib_classifier.py
src/information_bottleneck/ib_config.py
src/information_bottleneck/ib_optimizer.py
src/information_bottleneck/ib_visualization.py
src/information_bottleneck/information_bottleneck_wrapper_backup.py
src/information_bottleneck/ksg_mi_estimator.py
src/information_bottleneck/mi_estimation_config.py
src/information_bottleneck/mixins.py
src/information_bottleneck/mutual_info_core.py
src/information_bottleneck/mutual_info_estimator.py
src/information_bottleneck/neural_ib.py
src/information_bottleneck/research_accurate_solutions.py
src/information_bottleneck/visualization.py
src/information_bottleneck/config/__init__.py
src/information_bottleneck/config/enums.py
src/information_bottleneck/config/ib_config.py
src/information_bottleneck/core/__init__.py
src/information_bottleneck/core/classical_ib.py
src/information_bottleneck/core/deep_ib.py
src/information_bottleneck/core/ib_classifier.py
src/information_bottleneck/core/mutual_info.py
src/information_bottleneck/core/neural_ib.py
src/information_bottleneck/core/optimizer.py
src/information_bottleneck/mi_estimator_modules/__init__.py
src/information_bottleneck/mi_estimator_modules/base_estimator.py
src/information_bottleneck/mi_estimator_modules/binning_estimator.py
src/information_bottleneck/mi_estimator_modules/estimator_factory.py
src/information_bottleneck/mi_estimator_modules/ksg_estimator.py
src/information_bottleneck/old_archive/config_original.py
src/information_bottleneck/old_archive/information_bottleneck_original_3199_lines.py
src/information_bottleneck/old_archive/ksg_mi_estimator_original_1385_lines.py
src/information_bottleneck/old_archive/utils_original.py
information_bottleneck-1.3.0.dist-info/METADATA
information_bottleneck-1.3.0.dist-info/WHEEL
information_bottleneck-1.3.0.dist-info/licenses/LICENSE
information_bottleneck-1.3.0.dist-info/RECORD
